[
  {
    "id": 1,
    "make": "Toyota",
    "model": "Fortuner",
    "year": 2022,
    "price": 3500000,
    "images": [
      "https://images.unsplash.com/photo-1619682817481-e994891cd1f5?auto=format&fit=crop&q=80&w=800",
      "https://images.unsplash.com/photo-1583121274602-3e2820bc6988?auto=format&fit=crop&q=80&w=800",
      "https://images.unsplash.com/photo-1592906209472-a36b1f3782ef?auto=format&fit=crop&q=80&w=800"
    ]
  },
  {
    "id": 2,
    "make": "Hyundai",
    "model": "Creta",
    "year": 2021,
    "price": 1500000,
    "images": [
      "https://images.unsplash.com/photo-1619767886558-efdc259cde1a?auto=format&fit=crop&q=80&w=800",
      "https://images.unsplash.com/photo-1549317661-bd32c8ce0db2?auto=format&fit=crop&q=80&w=800",
      "https://images.unsplash.com/photo-1533473359331-0135ef1b58bf?auto=format&fit=crop&q=80&w=800"
    ]
  },
  {
    "id": 3,
    "make": "Maruti",
    "model": "Swift",
    "year": 2020,
    "price": 700000,
    "images": [
      "https://images.unsplash.com/photo-1567808291548-fc3ee04dbac0?auto=format&fit=crop&q=80&w=800",
      "https://images.unsplash.com/photo-1590362891175-379451245c40?auto=format&fit=crop&q=80&w=800",
      "https://images.unsplash.com/photo-1580273916550-e323be2ae537?auto=format&fit=crop&q=80&w=800"
    ]
  },
  {
    "id": 4,
    "make": "Tata",
    "model": "Nexon",
    "year": 2022,
    "price": 1200000,
    "images": [
      "https://images.unsplash.com/photo-1583267746897-2cf415888172?auto=format&fit=crop&q=80&w=800",
      "https://images.unsplash.com/photo-1611016186353-9af58c69a533?auto=format&fit=crop&q=80&w=800",
      "https://images.unsplash.com/photo-1532581133595-3004980ad54e?auto=format&fit=crop&q=80&w=800"
    ]
  },
  {
    "id": 5,
    "make": "Mahindra",
    "model": "Thar",
    "year": 2023,
    "price": 1800000,
    "images": [
      "https://images.unsplash.com/photo-1630659052733-407000e3650a?auto=format&fit=crop&q=80&w=800",
      "https://images.unsplash.com/photo-1621348248421-4d3756d112d8?auto=format&fit=crop&q=80&w=800",
      "https://images.unsplash.com/photo-1627443105658-94458385750d?auto=format&fit=crop&q=80&w=800"
    ]
  },
  {
    "id": 6,
    "make": "Kia",
    "model": "Seltos",
    "year": 2021,
    "price": 1400000,
    "images": [
      "https://images.unsplash.com/photo-1631835339300-3486df819385?auto=format&fit=crop&q=80&w=800",
      "https://images.unsplash.com/photo-1610647752706-3bb12232b3ab?auto=format&fit=crop&q=80&w=800",
      "https://images.unsplash.com/photo-1594502184342-2e12f877aa73?auto=format&fit=crop&q=80&w=800"
    ]
  },
  {
    "id": 7,
    "make": "Honda",
    "model": "City",
    "year": 2020,
    "price": 1300000,
    "images": [
      "https://images.unsplash.com/photo-1616438652309-8bc426b3e6e8?auto=format&fit=crop&q=80&w=800",
      "https://images.unsplash.com/photo-1549317661-bd32c8ce0db2?auto=format&fit=crop&q=80&w=800",
      "https://images.unsplash.com/photo-1580273916550-e323be2ae537?auto=format&fit=crop&q=80&w=800"
    ]
  },
  {
    "id": 8,
    "make": "Toyota",
    "model": "Innova Crysta",
    "year": 2022,
    "price": 2500000,
    "images": [
      "https://images.unsplash.com/photo-1621007947382-bb3c3994e3fb?auto=format&fit=crop&q=80&w=800",
      "https://images.unsplash.com/photo-1552519507-da3b142c6e3d?auto=format&fit=crop&q=80&w=800",
      "https://images.unsplash.com/photo-1605559424843-9e4c228bf1c2?auto=format&fit=crop&q=80&w=800"
    ]
  },
  {
    "id": 9,
    "make": "Hyundai",
    "model": "Verna",
    "year": 2021,
    "price": 1100000,
    "images": [
      "https://images.unsplash.com/photo-1553440569-bcc63803a83d?auto=format&fit=crop&q=80&w=800",
      "https://images.unsplash.com/photo-1549317661-bd32c8ce0db2?auto=format&fit=crop&q=80&w=800",
      "https://images.unsplash.com/photo-1533473359331-0135ef1b58bf?auto=format&fit=crop&q=80&w=800"
    ]
  },
  {
    "id": 10,
    "make": "Tata",
    "model": "Harrier",
    "year": 2023,
    "price": 2300000,
    "images": [
      "https://images.unsplash.com/photo-1615632126229-bc3d3328e342?auto=format&fit=crop&q=80&w=800",
      "https://images.unsplash.com/photo-1611016186353-9af58c69a533?auto=format&fit=crop&q=80&w=800",
      "https://images.unsplash.com/photo-1532581133595-3004980ad54e?auto=format&fit=crop&q=80&w=800"
    ]
  },
  {
    "id": 11,
    "make": "Mahindra",
    "model": "XUV700",
    "year": 2023,
    "price": 2600000,
    "images": [
      "https://images.unsplash.com/photo-1606148301667-46d47bf1455a?auto=format&fit=crop&q=80&w=800",
      "https://images.unsplash.com/photo-1550355291-bbee04a92027?auto=format&fit=crop&q=80&w=800",
      "https://images.unsplash.com/photo-1494976388531-d1058494cdd8?auto=format&fit=crop&q=80&w=800"
    ]
  },
  {
    "id": 12,
    "make": "Maruti",
    "model": "Baleno",
    "year": 2021,
    "price": 800000,
    "images": [
      "https://images.unsplash.com/photo-1617469767053-d3b503a0b12c?auto=format&fit=crop&q=80&w=800",
      "https://images.unsplash.com/photo-1511919884226-fd3cad34687c?auto=format&fit=crop&q=80&w=800",
      "https://images.unsplash.com/photo-1502877338535-766e1452684a?auto=format&fit=crop&q=80&w=800"
    ]
  },
  {
    "id": 13,
    "make": "Kia",
    "model": "Carens",
    "year": 2022,
    "price": 1600000,
    "images": [
      "https://images.unsplash.com/photo-1631835339300-3486df819385?auto=format&fit=crop&q=80&w=800",
      "https://images.unsplash.com/photo-1552519507-da3b142c6e3d?auto=format&fit=crop&q=80&w=800",
      "https://images.unsplash.com/photo-1503376780353-7e6692767b70?auto=format&fit=crop&q=80&w=800"
    ]
  },
  {
    "id": 14,
    "make": "Skoda",
    "model": "Slavia",
    "year": 2022,
    "price": 1400000,
    "images": [
      "https://images.unsplash.com/photo-1617469767053-d3b503a0b12c?auto=format&fit=crop&q=80&w=800",
      "https://images.unsplash.com/photo-1583121274602-3e2820bc6988?auto=format&fit=crop&q=80&w=800",
      "https://images.unsplash.com/photo-1511919884226-fd3cad34687c?auto=format&fit=crop&q=80&w=800"
    ]
  },
  {
    "id": 15,
    "make": "Volkswagen",
    "model": "Virtus",
    "year": 2022,
    "price": 1500000,
    "images": [
      "https://images.unsplash.com/photo-1599912027806-cfec9f5944b6?auto=format&fit=crop&q=80&w=800",
      "https://images.unsplash.com/photo-1542362567-b05260199732?auto=format&fit=crop&q=80&w=800",
      "https://images.unsplash.com/photo-1583121274602-3e2820bc6988?auto=format&fit=crop&q=80&w=800"
    ]
  },
  {
    "id": 16,
    "make": "Renault",
    "model": "Kiger",
    "year": 2021,
    "price": 900000,
    "images": [
      "https://images.unsplash.com/photo-1594502184342-2e12f877aa73?auto=format&fit=crop&q=80&w=800",
      "https://images.unsplash.com/photo-1619767886558-efdc259cde1a?auto=format&fit=crop&q=80&w=800",
      "https://images.unsplash.com/photo-1533473359331-0135ef1b58bf?auto=format&fit=crop&q=80&w=800"
    ]
  },
  {
    "id": 17,
    "make": "Nissan",
    "model": "Magnite",
    "year": 2021,
    "price": 850000,
    "images": [
      "https://images.unsplash.com/photo-1631835339300-3486df819385?auto=format&fit=crop&q=80&w=800",
      "https://images.unsplash.com/photo-1511919884226-fd3cad34687c?auto=format&fit=crop&q=80&w=800",
      "https://images.unsplash.com/photo-1502877338535-766e1452684a?auto=format&fit=crop&q=80&w=800"
    ]
  },
  {
    "id": 18,
    "make": "BMW",
    "model": "X5",
    "year": 2023,
    "price": 9500000,
    "images": [
      "https://images.unsplash.com/photo-1555215695-3004980ad54e?auto=format&fit=crop&q=80&w=800",
      "https://images.unsplash.com/photo-1556189250-72ba954cfc2b?auto=format&fit=crop&q=80&w=800",
      "https://images.unsplash.com/photo-1605559424843-9e4c228bf1c2?auto=format&fit=crop&q=80&w=800"
    ]
  },
  {
    "id": 19,
    "make": "Audi",
    "model": "Q7",
    "year": 2022,
    "price": 9000000,
    "images": [
      "https://images.unsplash.com/photo-1562620644-66bd327e53f7?auto=format&fit=crop&q=80&w=800",
      "https://images.unsplash.com/photo-1542282088-fe8426682b8f?auto=format&fit=crop&q=80&w=800",
      "https://images.unsplash.com/photo-1533473359331-0135ef1b58bf?auto=format&fit=crop&q=80&w=800"
    ]
  },
  {
    "id": 20,
    "make": "Mercedes",
    "model": "GLA",
    "year": 2022,
    "price": 5500000,
    "images": [
      "https://images.unsplash.com/photo-1618843479313-40f8afb4b4d8?auto=format&fit=crop&q=80&w=800",
      "https://images.unsplash.com/photo-1553440569-bcc63803a83d?auto=format&fit=crop&q=80&w=800",
      "https://images.unsplash.com/photo-1614162692292-7ac56d7f7f1e?auto=format&fit=crop&q=80&w=800"
    ]
  },
  {
    "id": 21,
    "make": "Jeep",
    "model": "Compass",
    "year": 2021,
    "price": 2400000,
    "images": [
      "https://images.unsplash.com/photo-1539108190285-bc5b37877c8e?auto=format&fit=crop&q=80&w=800",
      "https://images.unsplash.com/photo-1610647752706-3bb12232b3ab?auto=format&fit=crop&q=80&w=800",
      "https://images.unsplash.com/photo-1621348248421-4d3756d112d8?auto=format&fit=crop&q=80&w=800"
    ]
  },
  {
    "id": 22,
    "make": "MG",
    "model": "Hector",
    "year": 2022,
    "price": 2100000,
    "images": [
      "https://images.unsplash.com/photo-1549317661-bd32c8ce0db2?auto=format&fit=crop&q=80&w=800",
      "https://images.unsplash.com/photo-1610647752706-3bb12232b3ab?auto=format&fit=crop&q=80&w=800",
      "https://images.unsplash.com/photo-1583121274602-3e2820bc6988?auto=format&fit=crop&q=80&w=800"
    ]
  },
  {
    "id": 23,
    "make": "Toyota",
    "model": "Glanza",
    "year": 2021,
    "price": 750000,
    "images": [
      "https://images.unsplash.com/photo-1511919884226-fd3cad34687c?auto=format&fit=crop&q=80&w=800",
      "https://images.unsplash.com/photo-1502877338535-766e1452684a?auto=format&fit=crop&q=80&w=800",
      "https://images.unsplash.com/photo-1503376780353-7e6692767b70?auto=format&fit=crop&q=80&w=800"
    ]
  },
  {
    "id": 24,
    "make": "Hyundai",
    "model": "i20",
    "year": 2022,
    "price": 900000,
    "images": [
      "https://images.unsplash.com/photo-1549317661-bd32c8ce0db2?auto=format&fit=crop&q=80&w=800",
      "https://images.unsplash.com/photo-1617469767053-d3b503a0b12c?auto=format&fit=crop&q=80&w=800",
      "https://images.unsplash.com/photo-1567808291548-fc3ee04dbac0?auto=format&fit=crop&q=80&w=800"
    ]
  },
  {
    "id": 25,
    "make": "Tata",
    "model": "Punch",
    "year": 2023,
    "price": 700000,
    "images": [
      "https://images.unsplash.com/photo-1594502184342-2e12f877aa73?auto=format&fit=crop&q=80&w=800",
      "https://images.unsplash.com/photo-1611016186353-9af58c69a533?auto=format&fit=crop&q=80&w=800",
      "https://images.unsplash.com/photo-1532581133595-3004980ad54e?auto=format&fit=crop&q=80&w=800"
    ]
  },
  {
    "id": 26,
    "make": "Maruti",
    "model": "Ertiga",
    "year": 2022,
    "price": 1100000,
    "images": [
      "https://images.unsplash.com/photo-1621007947382-bb3c3994e3fb?auto=format&fit=crop&q=80&w=800",
      "https://images.unsplash.com/photo-1552519507-da3b142c6e3d?auto=format&fit=crop&q=80&w=800",
      "https://images.unsplash.com/photo-1605559424843-9e4c228bf1c2?auto=format&fit=crop&q=80&w=800"
    ]
  },
  {
    "id": 27,
    "make": "Honda",
    "model": "Amaze",
    "year": 2021,
    "price": 800000,
    "images": [
      "https://images.unsplash.com/photo-1616438652309-8bc426b3e6e8?auto=format&fit=crop&q=80&w=800",
      "https://images.unsplash.com/photo-1549317661-bd32c8ce0db2?auto=format&fit=crop&q=80&w=800",
      "https://images.unsplash.com/photo-1503376780353-7e6692767b70?auto=format&fit=crop&q=80&w=800"
    ]
  },
  {
    "id": 28,
    "make": "Toyota",
    "model": "Urban Cruiser",
    "year": 2022,
    "price": 1150000,
    "images": [
      "https://images.unsplash.com/photo-1619682817481-e994891cd1f5?auto=format&fit=crop&q=80&w=800",
      "https://images.unsplash.com/photo-1610647752706-3bb12232b3ab?auto=format&fit=crop&q=80&w=800",
      "https://images.unsplash.com/photo-1533473359331-0135ef1b58bf?auto=format&fit=crop&q=80&w=800"
    ]
  },
  {
    "id": 29,
    "make": "Kia",
    "model": "Sonet",
    "year": 2022,
    "price": 1050000,
    "images": [
      "https://images.unsplash.com/photo-1631835339300-3486df819385?auto=format&fit=crop&q=80&w=800",
      "https://images.unsplash.com/photo-1594502184342-2e12f877aa73?auto=format&fit=crop&q=80&w=800",
      "https://images.unsplash.com/photo-1502877338535-766e1452684a?auto=format&fit=crop&q=80&w=800"
    ]
  },
  {
    "id": 30,
    "make": "Hyundai",
    "model": "Venue",
    "year": 2021,
    "price": 1000000,
    "images": [
      "https://images.unsplash.com/photo-1619767886558-efdc259cde1a?auto=format&fit=crop&q=80&w=800",
      "https://images.unsplash.com/photo-1549317661-bd32c8ce0db2?auto=format&fit=crop&q=80&w=800",
      "https://images.unsplash.com/photo-1533473359331-0135ef1b58bf?auto=format&fit=crop&q=80&w=800"
    ]
  },
  {
    "id": 31,
    "make": "Tata",
    "model": "Altroz",
    "year": 2022,
    "price": 800000,
    "images": [
      "https://images.unsplash.com/photo-1617469767053-d3b503a0b12c?auto=format&fit=crop&q=80&w=800",
      "https://images.unsplash.com/photo-1567808291548-fc3ee04dbac0?auto=format&fit=crop&q=80&w=800",
      "https://images.unsplash.com/photo-1511919884226-fd3cad34687c?auto=format&fit=crop&q=80&w=800"
    ]
  },
  {
    "id": 32,
    "make": "Mahindra",
    "model": "Scorpio N",
    "year": 2023,
    "price": 2000000,
    "images": [
      "https://images.unsplash.com/photo-1606148301667-46d47bf1455a?auto=format&fit=crop&q=80&w=800",
      "https://images.unsplash.com/photo-1621348248421-4d3756d112d8?auto=format&fit=crop&q=80&w=800",
      "https://images.unsplash.com/photo-1630659052733-407000e3650a?auto=format&fit=crop&q=80&w=800"
    ]
  },
  {
    "id": 33,
    "make": "Skoda",
    "model": "Kushaq",
    "year": 2022,
    "price": 1600000,
    "images": [
      "https://images.unsplash.com/photo-1610647752706-3bb12232b3ab?auto=format&fit=crop&q=80&w=800",
      "https://images.unsplash.com/photo-1583121274602-3e2820bc6988?auto=format&fit=crop&q=80&w=800",
      "https://images.unsplash.com/photo-1550355291-bbee04a92027?auto=format&fit=crop&q=80&w=800"
    ]
  },
  {
    "id": 34,
    "make": "Volkswagen",
    "model": "Taigun",
    "year": 2022,
    "price": 1550000,
    "images": [
      "https://images.unsplash.com/photo-1599912027806-cfec9f5944b6?auto=format&fit=crop&q=80&w=800",
      "https://images.unsplash.com/photo-1619767886558-efdc259cde1a?auto=format&fit=crop&q=80&w=800",
      "https://images.unsplash.com/photo-1542362567-b05260199732?auto=format&fit=crop&q=80&w=800"
    ]
  },
  {
    "id": 35,
    "make": "Renault",
    "model": "Triber",
    "year": 2021,
    "price": 700000,
    "images": [
      "https://images.unsplash.com/photo-1621007947382-bb3c3994e3fb?auto=format&fit=crop&q=80&w=800",
      "https://images.unsplash.com/photo-1552519507-da3b142c6e3d?auto=format&fit=crop&q=80&w=800",
      "https://images.unsplash.com/photo-1503376780353-7e6692767b70?auto=format&fit=crop&q=80&w=800"
    ]
  },
  {
    "id": 36,
    "make": "Nissan",
    "model": "Kicks",
    "year": 2020,
    "price": 1200000,
    "images": [
      "https://images.unsplash.com/photo-1631835339300-3486df819385?auto=format&fit=crop&q=80&w=800",
      "https://images.unsplash.com/photo-1610647752706-3bb12232b3ab?auto=format&fit=crop&q=80&w=800",
      "https://images.unsplash.com/photo-1594502184342-2e12f877aa73?auto=format&fit=crop&q=80&w=800"
    ]
  },
  {
    "id": 37,
    "make": "MG",
    "model": "Astor",
    "year": 2022,
    "price": 1500000,
    "images": [
      "https://images.unsplash.com/photo-1549317661-bd32c8ce0db2?auto=format&fit=crop&q=80&w=800",
      "https://images.unsplash.com/photo-1610647752706-3bb12232b3ab?auto=format&fit=crop&q=80&w=800",
      "https://images.unsplash.com/photo-1583121274602-3e2820bc6988?auto=format&fit=crop&q=80&w=800"
    ]
  },
  {
    "id": 38,
    "make": "Jeep",
    "model": "Meridian",
    "year": 2022,
    "price": 3300000,
    "images": [
      "https://images.unsplash.com/photo-1539108190285-bc5b37877c8e?auto=format&fit=crop&q=80&w=800",
      "https://images.unsplash.com/photo-1610647752706-3bb12232b3ab?auto=format&fit=crop&q=80&w=800",
      "https://images.unsplash.com/photo-1550355291-bbee04a92027?auto=format&fit=crop&q=80&w=800"
    ]
  },
  {
    "id": 39,
    "make": "BMW",
    "model": "3 Series",
    "year": 2022,
    "price": 7200000,
    "images": [
      "https://images.unsplash.com/photo-1555215695-3004980ad54e?auto=format&fit=crop&q=80&w=800",
      "https://images.unsplash.com/photo-1556189250-72ba954cfc2b?auto=format&fit=crop&q=80&w=800",
      "https://images.unsplash.com/photo-1605559424843-9e4c228bf1c2?auto=format&fit=crop&q=80&w=800"
    ]
  },
  {
    "id": 40,
    "make": "Audi",
    "model": "A4",
    "year": 2021,
    "price": 6000000,
    "images": [
      "https://images.unsplash.com/photo-1562620644-66bd327e53f7?auto=format&fit=crop&q=80&w=800",
      "https://images.unsplash.com/photo-1542282088-fe8426682b8f?auto=format&fit=crop&q=80&w=800",
      "https://images.unsplash.com/photo-1533473359331-0135ef1b58bf?auto=format&fit=crop&q=80&w=800"
    ]
  },
  {
    "id": 41,
    "make": "Mercedes",
    "model": "C-Class",
    "year": 2022,
    "price": 6500000,
    "images": [
      "https://images.unsplash.com/photo-1618843479313-40f8afb4b4d8?auto=format&fit=crop&q=80&w=800",
      "https://images.unsplash.com/photo-1553440569-bcc63803a83d?auto=format&fit=crop&q=80&w=800",
      "https://images.unsplash.com/photo-1614162692292-7ac56d7f7f1e?auto=format&fit=crop&q=80&w=800"
    ]
  },
  {
    "id": 42,
    "make": "Volvo",
    "model": "XC40",
    "year": 2022,
    "price": 4500000,
    "images": [
      "https://images.unsplash.com/photo-1617469767053-d3b503a0b12c?auto=format&fit=crop&q=80&w=800",
      "https://images.unsplash.com/photo-1583121274602-3e2820bc6988?auto=format&fit=crop&q=80&w=800",
      "https://images.unsplash.com/photo-1550355291-bbee04a92027?auto=format&fit=crop&q=80&w=800"
    ]
  },
  {
    "id": 43,
    "make": "Lexus",
    "model": "NX",
    "year": 2023,
    "price": 6800000,
    "images": [
      "https://images.unsplash.com/photo-1618843479313-40f8afb4b4d8?auto=format&fit=crop&q=80&w=800",
      "https://images.unsplash.com/photo-1553440569-bcc63803a83d?auto=format&fit=crop&q=80&w=800",
      "https://images.unsplash.com/photo-1614162692292-7ac56d7f7f1e?auto=format&fit=crop&q=80&w=800"
    ]
  },
  {
    "id": 44,
    "make": "Porsche",
    "model": "Macan",
    "year": 2022,
    "price": 8500000,
    "images": [
      "https://images.unsplash.com/photo-1503376780353-7e6692767b70?auto=format&fit=crop&q=80&w=800",
      "https://images.unsplash.com/photo-1580273916550-e323be2ae537?auto=format&fit=crop&q=80&w=800",
      "https://images.unsplash.com/photo-1614162692292-7ac56d7f7f1e?auto=format&fit=crop&q=80&w=800"
    ]
  },
  {
    "id": 45,
    "make": "Land Rover",
    "model": "Discovery Sport",
    "year": 2021,
    "price": 7200000,
    "images": [
      "https://images.unsplash.com/photo-1552519507-da3b142c6e3d?auto=format&fit=crop&q=80&w=800",
      "https://images.unsplash.com/photo-1550355291-bbee04a92027?auto=format&fit=crop&q=80&w=800",
      "https://images.unsplash.com/photo-1533473359331-0135ef1b58bf?auto=format&fit=crop&q=80&w=800"
    ]
  },
  {
    "id": 46,
    "make": "Jaguar",
    "model": "F-Pace",
    "year": 2022,
    "price": 7800000,
    "images": [
      "https://images.unsplash.com/photo-1614162692292-7ac56d7f7f1e?auto=format&fit=crop&q=80&w=800",
      "https://images.unsplash.com/photo-1553440569-bcc63803a83d?auto=format&fit=crop&q=80&w=800",
      "https://images.unsplash.com/photo-1618843479313-40f8afb4b4d8?auto=format&fit=crop&q=80&w=800"
    ]
  },
  {
    "id": 47,
    "make": "Mini",
    "model": "Cooper",
    "year": 2021,
    "price": 4500000,
    "images": [
      "https://images.unsplash.com/photo-1590362891175-379451245c40?auto=format&fit=crop&q=80&w=800",
      "https://images.unsplash.com/photo-1567808291548-fc3ee04dbac0?auto=format&fit=crop&q=80&w=800",
      "https://images.unsplash.com/photo-1511919884226-fd3cad34687c?auto=format&fit=crop&q=80&w=800"
    ]
  },
  {
    "id": 48,
    "make": "Tesla",
    "model": "Model 3",
    "year": 2023,
    "price": 5500000,
    "images": [
      "https://images.unsplash.com/photo-1560958089-b8a1929cea89?auto=format&fit=crop&q=80&w=800",
      "https://images.unsplash.com/photo-1561580119-7d90193c7233?auto=format&fit=crop&q=80&w=800",
      "https://images.unsplash.com/photo-1536700503339-1e4b06520771?auto=format&fit=crop&q=80&w=800"
    ]
  },
  {
    "id": 49,
    "make": "Tesla",
    "model": "Model Y",
    "year": 2023,
    "price": 6500000,
    "images": [
      "https://images.unsplash.com/photo-1619767886558-efdc259cde1a?auto=format&fit=crop&q=80&w=800",
      "https://images.unsplash.com/photo-1553440569-bcc63803a83d?auto=format&fit=crop&q=80&w=800",
      "https://images.unsplash.com/photo-1560958089-b8a1929cea89?auto=format&fit=crop&q=80&w=800"
    ]
  },
  {
    "id": 50,
    "make": "BYD",
    "model": "Atto 3",
    "year": 2023,
    "price": 3300000,
    "images": [
      "https://images.unsplash.com/photo-1593941707882-a5bba14938c7?auto=format&fit=crop&q=80&w=800",
      "https://images.unsplash.com/photo-1511919884226-fd3cad34687c?auto=format&fit=crop&q=80&w=800",
      "https://images.unsplash.com/photo-1560958089-b8a1929cea89?auto=format&fit=crop&q=80&w=800"
    ]
  },
  {
    "id": 51,
    "make": "Tata",
    "model": "Safari",
    "year": 2023,
    "price": 2800000,
    "images": [
      "https://images.unsplash.com/photo-1611016186353-9af58c69a533?auto=format&fit=crop&q=80&w=800",
      "https://images.unsplash.com/photo-1532581133595-3004980ad54e?auto=format&fit=crop&q=80&w=800",
      "https://images.unsplash.com/photo-1583267746897-2cf415888172?auto=format&fit=crop&q=80&w=800"
    ]
  },
  {
    "id": 52,
    "make": "Hyundai",
    "model": "Tucson",
    "year": 2022,
    "price": 2900000,
    "images": [
      "https://images.unsplash.com/photo-1619767886558-efdc259cde1a?auto=format&fit=crop&q=80&w=800",
      "https://images.unsplash.com/photo-1549317661-bd32c8ce0db2?auto=format&fit=crop&q=80&w=800",
      "https://images.unsplash.com/photo-1533473359331-0135ef1b58bf?auto=format&fit=crop&q=80&w=800"
    ]
  },
  {
    "id": 53,
    "make": "Toyota",
    "model": "Camry",
    "year": 2022,
    "price": 4500000,
    "images": [
      "https://images.unsplash.com/photo-1616438652309-8bc426b3e6e8?auto=format&fit=crop&q=80&w=800",
      "https://images.unsplash.com/photo-1583121274602-3e2820bc6988?auto=format&fit=crop&q=80&w=800",
      "https://images.unsplash.com/photo-1511919884226-fd3cad34687c?auto=format&fit=crop&q=80&w=800"
    ]
  },
  {
    "id": 54,
    "make": "Honda",
    "model": "Civic",
    "year": 2021,
    "price": 2200000,
    "images": [
      "https://images.unsplash.com/photo-1616438652309-8bc426b3e6e8?auto=format&fit=crop&q=80&w=800",
      "https://images.unsplash.com/photo-1549317661-bd32c8ce0db2?auto=format&fit=crop&q=80&w=800",
      "https://images.unsplash.com/photo-1503376780353-7e6692767b70?auto=format&fit=crop&q=80&w=800"
    ]
  },
  {
    "id": 55,
    "make": "Skoda",
    "model": "Octavia",
    "year": 2022,
    "price": 3000000,
    "images": [
      "https://images.unsplash.com/photo-1583121274602-3e2820bc6988?auto=format&fit=crop&q=80&w=800",
      "https://images.unsplash.com/photo-1511919884226-fd3cad34687c?auto=format&fit=crop&q=80&w=800",
      "https://images.unsplash.com/photo-1550355291-bbee04a92027?auto=format&fit=crop&q=80&w=800"
    ]
  },
  {
    "id": 56,
    "make": "Volkswagen",
    "model": "Passat",
    "year": 2021,
    "price": 3200000,
    "images": [
      "https://images.unsplash.com/photo-1599912027806-cfec9f5944b6?auto=format&fit=crop&q=80&w=800",
      "https://images.unsplash.com/photo-1542362567-b05260199732?auto=format&fit=crop&q=80&w=800",
      "https://images.unsplash.com/photo-1583121274602-3e2820bc6988?auto=format&fit=crop&q=80&w=800"
    ]
  },
  {
    "id": 57,
    "make": "Ford",
    "model": "Endeavour",
    "year": 2020,
    "price": 3500000,
    "images": [
      "https://images.unsplash.com/photo-1533473359331-0135ef1b58bf?auto=format&fit=crop&q=80&w=800",
      "https://images.unsplash.com/photo-1610647752706-3bb12232b3ab?auto=format&fit=crop&q=80&w=800",
      "https://images.unsplash.com/photo-1621348248421-4d3756d112d8?auto=format&fit=crop&q=80&w=800"
    ]
  },
  {
    "id": 58,
    "make": "Isuzu",
    "model": "D-Max",
    "year": 2021,
    "price": 1800000,
    "images": [
      "https://images.unsplash.com/photo-1606148301667-46d47bf1455a?auto=format&fit=crop&q=80&w=800",
      "https://images.unsplash.com/photo-1550355291-bbee04a92027?auto=format&fit=crop&q=80&w=800",
      "https://images.unsplash.com/photo-1494976388531-d1058494cdd8?auto=format&fit=crop&q=80&w=800"
    ]
  },
  {
    "id": 59,
    "make": "Mitsubishi",
    "model": "Pajero Sport",
    "year": 2019,
    "price": 2800000,
    "images": [
      "https://images.unsplash.com/photo-1552519507-da3b142c6e3d?auto=format&fit=crop&q=80&w=800",
      "https://images.unsplash.com/photo-1610647752706-3bb12232b3ab?auto=format&fit=crop&q=80&w=800",
      "https://images.unsplash.com/photo-1621348248421-4d3756d112d8?auto=format&fit=crop&q=80&w=800"
    ]
  },
  {
    "id": 60,
    "make": "Chevrolet",
    "model": "Trailblazer",
    "year": 2020,
    "price": 2600000,
    "images": [
      "https://images.unsplash.com/photo-1610647752706-3bb12232b3ab?auto=format&fit=crop&q=80&w=800",
      "https://images.unsplash.com/photo-1533473359331-0135ef1b58bf?auto=format&fit=crop&q=80&w=800",
      "https://images.unsplash.com/photo-1621348248421-4d3756d112d8?auto=format&fit=crop&q=80&w=800"
    ]
  },
  {
    "id": 61,
    "make": "Peugeot",
    "model": "3008",
    "year": 2022,
    "price": 3400000,
    "images": [
      "https://images.unsplash.com/photo-1610647752706-3bb12232b3ab?auto=format&fit=crop&q=80&w=800",
      "https://images.unsplash.com/photo-1619767886558-efdc259cde1a?auto=format&fit=crop&q=80&w=800",
      "https://images.unsplash.com/photo-1533473359331-0135ef1b58bf?auto=format&fit=crop&q=80&w=800"
    ]
  },
  {
    "id": 62,
    "make": "Citroen",
    "model": "C5 Aircross",
    "year": 2021,
    "price": 3200000,
    "images": [
      "https://images.unsplash.com/photo-1610647752706-3bb12232b3ab?auto=format&fit=crop&q=80&w=800",
      "https://images.unsplash.com/photo-1619767886558-efdc259cde1a?auto=format&fit=crop&q=80&w=800",
      "https://images.unsplash.com/photo-1533473359331-0135ef1b58bf?auto=format&fit=crop&q=80&w=800"
    ]
  },
  {
    "id": 63,
    "make": "Subaru",
    "model": "Forester",
    "year": 2020,
    "price": 3000000,
    "images": [
      "https://images.unsplash.com/photo-1610647752706-3bb12232b3ab?auto=format&fit=crop&q=80&w=800",
      "https://images.unsplash.com/photo-1619767886558-efdc259cde1a?auto=format&fit=crop&q=80&w=800",
      "https://images.unsplash.com/photo-1533473359331-0135ef1b58bf?auto=format&fit=crop&q=80&w=800"
    ]
  },
  {
    "id": 64,
    "make": "Mazda",
    "model": "CX-5",
    "year": 2021,
    "price": 2800000,
    "images": [
      "https://images.unsplash.com/photo-1610647752706-3bb12232b3ab?auto=format&fit=crop&q=80&w=800",
      "https://images.unsplash.com/photo-1619767886558-efdc259cde1a?auto=format&fit=crop&q=80&w=800",
      "https://images.unsplash.com/photo-1533473359331-0135ef1b58bf?auto=format&fit=crop&q=80&w=800"
    ]
  },
  {
    "id": 65,
    "make": "Suzuki",
    "model": "Jimny",
    "year": 2023,
    "price": 1600000,
    "images": [
      "https://images.unsplash.com/photo-1630659052733-407000e3650a?auto=format&fit=crop&q=80&w=800",
      "https://images.unsplash.com/photo-1621348248421-4d3756d112d8?auto=format&fit=crop&q=80&w=800",
      "https://images.unsplash.com/photo-1627443105658-94458385750d?auto=format&fit=crop&q=80&w=800"
    ]
  },
  {
    "id": 66,
    "make": "Tata",
    "model": "Tiago EV",
    "year": 2023,
    "price": 900000,
    "images": [
      "https://images.unsplash.com/photo-1593941707882-a5bba14938c7?auto=format&fit=crop&q=80&w=800",
      "https://images.unsplash.com/photo-1511919884226-fd3cad34687c?auto=format&fit=crop&q=80&w=800",
      "https://images.unsplash.com/photo-1502877338535-766e1452684a?auto=format&fit=crop&q=80&w=800"
    ]
  },
  {
    "id": 67,
    "make": "MG",
    "model": "ZS EV",
    "year": 2022,
    "price": 2300000,
    "images": [
      "https://images.unsplash.com/photo-1593941707882-a5bba14938c7?auto=format&fit=crop&q=80&w=800",
      "https://images.unsplash.com/photo-1610647752706-3bb12232b3ab?auto=format&fit=crop&q=80&w=800",
      "https://images.unsplash.com/photo-1619767886558-efdc259cde1a?auto=format&fit=crop&q=80&w=800"
    ]
  },
  {
    "id": 68,
    "make": "Hyundai",
    "model": "Ioniq 5",
    "year": 2023,
    "price": 4500000,
    "images": [
      "https://images.unsplash.com/photo-1619767886558-efdc259cde1a?auto=format&fit=crop&q=80&w=800",
      "https://images.unsplash.com/photo-1593941707882-a5bba14938c7?auto=format&fit=crop&q=80&w=800",
      "https://images.unsplash.com/photo-1560958089-b8a1929cea89?auto=format&fit=crop&q=80&w=800"
    ]
  },
  {
    "id": 69,
    "make": "BMW",
    "model": "iX",
    "year": 2023,
    "price": 12000000,
    "images": [
      "https://images.unsplash.com/photo-1555215695-3004980ad54e?auto=format&fit=crop&q=80&w=800",
      "https://images.unsplash.com/photo-1593941707882-a5bba14938c7?auto=format&fit=crop&q=80&w=800",
      "https://images.unsplash.com/photo-1561580119-7d90193c7233?auto=format&fit=crop&q=80&w=800"
    ]
  },
  {
    "id": 70,
    "make": "Audi",
    "model": "e-tron",
    "year": 2022,
    "price": 11000000,
    "images": [
      "https://images.unsplash.com/photo-1562620644-66bd327e53f7?auto=format&fit=crop&q=80&w=800",
      "https://images.unsplash.com/photo-1593941707882-a5bba14938c7?auto=format&fit=crop&q=80&w=800",
      "https://images.unsplash.com/photo-1561580119-7d90193c7233?auto=format&fit=crop&q=80&w=800"
    ]
  },
  {
    "id": 71,
    "make": "Mercedes",
    "model": "EQB",
    "year": 2023,
    "price": 7700000,
    "images": [
      "https://images.unsplash.com/photo-1618843479313-40f8afb4b4d8?auto=format&fit=crop&q=80&w=800",
      "https://images.unsplash.com/photo-1593941707882-a5bba14938c7?auto=format&fit=crop&q=80&w=800",
      "https://images.unsplash.com/photo-1561580119-7d90193c7233?auto=format&fit=crop&q=80&w=800"
    ]
  },
  {
    "id": 72,
    "make": "Porsche",
    "model": "Taycan",
    "year": 2022,
    "price": 15000000,
    "images": [
      "https://images.unsplash.com/photo-1614162692292-7ac56d7f7f1e?auto=format&fit=crop&q=80&w=800",
      "https://images.unsplash.com/photo-1593941707882-a5bba14938c7?auto=format&fit=crop&q=80&w=800",
      "https://images.unsplash.com/photo-1561580119-7d90193c7233?auto=format&fit=crop&q=80&w=800"
    ]
  },
  {
    "id": 73,
    "make": "Lamborghini",
    "model": "Urus",
    "year": 2022,
    "price": 35000000,
    "images": [
      "https://images.unsplash.com/photo-1544636331-e26879cd4d9b?auto=format&fit=crop&q=80&w=800",
      "https://images.unsplash.com/photo-1580273916550-e323be2ae537?auto=format&fit=crop&q=80&w=800",
      "https://images.unsplash.com/photo-1614162692292-7ac56d7f7f1e?auto=format&fit=crop&q=80&w=800"
    ]
  },
  {
    "id": 74,
    "make": "Ferrari",
    "model": "Roma",
    "year": 2021,
    "price": 38000000,
    "images": [
      "https://images.unsplash.com/photo-1583121274602-3e2820bc6988?auto=format&fit=crop&q=80&w=800",
      "https://images.unsplash.com/photo-1592198084033-aade902d1aae?auto=format&fit=crop&q=80&w=800",
      "https://images.unsplash.com/photo-1614162692292-7ac56d7f7f1e?auto=format&fit=crop&q=80&w=800"
    ]
  },
  {
    "id": 75,
    "make": "Rolls Royce",
    "model": "Cullinan",
    "year": 2022,
    "price": 70000000,
    "images": [
      "https://images.unsplash.com/photo-1631214524020-5e1f74dd7c42?auto=format&fit=crop&q=80&w=800",
      "https://images.unsplash.com/photo-1550355291-bbee04a92027?auto=format&fit=crop&q=80&w=800",
      "https://images.unsplash.com/photo-1614162692292-7ac56d7f7f1e?auto=format&fit=crop&q=80&w=800"
    ]
  }
]